{"name":"Corona Confirmed Cases","description":"","version":"1.0","culture":"en-GB","modifiedTime":"2020-03-01T07:11:38.8893179+00:00","pbi:mashup":{"fastCombine":false,"allowNativeQueries":false,"queriesMetadata":{"Corona Confirmed Cases":{"queryId":"9117b23e-26c8-4ac6-a3d3-eb5546f90ba7","queryName":"Corona Confirmed Cases","loadEnabled":true}},"document":"section Section1;\r\nshared #\"Corona Confirmed Cases\" = let\r\n  Source = Csv.Document(Web.Contents(\"https://raw.githubusercontent.com/CSSEGISandData/COVID-19/master/csse_covid_19_data/csse_covid_19_time_series/time_series_19-covid-Confirmed.csv\"), [Delimiter = \",\", QuoteStyle = QuoteStyle.None]),\r\n  #\"Changed column type\" = Table.TransformColumnTypes(Source, {{\"Column1\", type text}, {\"Column2\", type text}, {\"Column3\", type text}, {\"Column4\", type text}, {\"Column5\", type text}, {\"Column6\", type text}, {\"Column7\", type text}, {\"Column8\", type text}, {\"Column9\", type text}, {\"Column10\", type text}, {\"Column11\", type text}, {\"Column12\", type text}, {\"Column13\", type text}, {\"Column14\", type text}, {\"Column15\", type text}, {\"Column16\", type text}, {\"Column17\", type text}, {\"Column18\", type text}, {\"Column19\", type text}, {\"Column20\", type text}, {\"Column21\", type text}, {\"Column22\", type text}, {\"Column23\", type text}, {\"Column24\", type text}, {\"Column25\", type text}, {\"Column26\", type text}, {\"Column27\", type text}, {\"Column28\", type text}, {\"Column29\", type text}, {\"Column30\", type text}, {\"Column31\", type text}, {\"Column32\", type text}, {\"Column33\", type text}, {\"Column34\", type text}, {\"Column35\", type text}, {\"Column36\", type text}, {\"Column37\", type text}, {\"Column38\", type text}, {\"Column39\", type text}, {\"Column40\", type text}, {\"Column41\", type text}, {\"Column42\", type text}}),\r\n  #\"Promoted headers\" = Table.PromoteHeaders(#\"Changed column type\", [PromoteAllScalars = true]),\r\n  #\"Changed column type 1\" = Table.TransformColumnTypes(#\"Promoted headers\", {{\"Province/State\", type text}, {\"Country/Region\", type text}, {\"Lat\", type number}, {\"Long\", type number}, {\"1/22/20\", Int64.Type}, {\"1/23/20\", Int64.Type}, {\"1/24/20\", Int64.Type}, {\"1/25/20\", Int64.Type}, {\"1/26/20\", Int64.Type}, {\"1/27/20\", Int64.Type}, {\"1/28/20\", Int64.Type}, {\"1/29/20\", Int64.Type}, {\"1/30/20\", Int64.Type}, {\"1/31/20\", Int64.Type}, {\"2/1/20\", Int64.Type}, {\"2/2/20\", Int64.Type}, {\"2/3/20\", Int64.Type}, {\"2/4/20\", Int64.Type}, {\"2/5/20\", Int64.Type}, {\"2/6/20\", Int64.Type}, {\"2/7/20\", Int64.Type}, {\"2/8/20\", Int64.Type}, {\"2/9/20\", Int64.Type}, {\"2/10/20\", Int64.Type}, {\"2/11/20\", Int64.Type}, {\"2/12/20\", Int64.Type}, {\"2/13/20\", Int64.Type}, {\"2/14/20\", Int64.Type}, {\"2/15/20\", Int64.Type}, {\"2/16/20\", Int64.Type}, {\"2/17/20\", Int64.Type}, {\"2/18/20\", Int64.Type}, {\"2/19/20\", Int64.Type}, {\"2/20/20\", Int64.Type}, {\"2/21/20\", Int64.Type}, {\"2/22/20\", Int64.Type}, {\"2/23/20\", Int64.Type}, {\"2/24/20\", Int64.Type}, {\"2/25/20\", Int64.Type}, {\"2/26/20\", Int64.Type}, {\"2/27/20\", Int64.Type}, {\"2/28/20\", Int64.Type}}),\r\n  #\"Unpivoted columns\" = Table.UnpivotOtherColumns(#\"Changed column type 1\", {\"Province/State\", \"Country/Region\", \"Lat\", \"Long\"}, \"Attribute\", \"Value\"),\r\n  #\"Changed column type 2\" = Table.TransformColumnTypes(#\"Unpivoted columns\", {{\"Value\", Int64.Type}}),\r\n  #\"Renamed columns\" = Table.RenameColumns(#\"Changed column type 2\", {{\"Attribute\", \"Date\"}, {\"Value\", \"Confirmed Cases\"}})\r\nin\r\n  #\"Renamed columns\";\r\n"},"annotations":[{"name":"pbi:QueryGroups","value":"[]"}],"entities":[{"$type":"LocalEntity","name":"Corona Confirmed Cases","description":"","pbi:refreshPolicy":{"$type":"FullRefreshPolicy","location":"Corona%20Confirmed%20Cases.csv"},"attributes":[{"name":"Province/State","dataType":"string"},{"name":"Country/Region","dataType":"string"},{"name":"Lat","dataType":"double"},{"name":"Long","dataType":"double"},{"name":"Date","dataType":"string"},{"name":"Confirmed Cases","dataType":"int64"}],"partitions":[{"name":"Part001","refreshTime":"2020-03-02T09:46:53.8580849+00:00","location":"https://wabiauseaapcdsap1.blob.core.windows.net:443/83ad6759-2875-4992-bc0b-51e701cbc178/Corona%2520Confirmed%2520Cases.csv?snapshot=2020-03-02T09%3A46%3A53.8516150Z"}]}]}